{
    "name": "fluidsynth",
    "buildsystem": "cmake",
    "config-opts": [
        "-DLIB_SUFFIX=''"
    ],
    "sources": [
        {
            "type": "archive",
            "url": "https://github.com/FluidSynth/fluidsynth/archive/v2.2.3.tar.gz",
            "sha256": "b31807cb0f88e97f3096e2b378c9815a6acfdc20b0b14f97936d905b536965c4",
            "x-checker-data": {
                "type": "anitya",
                "project-id": 10437,
                "stable-only": true,
                "url-template": "https://github.com/FluidSynth/fluidsynth/archive/v$version.tar.gz"
            }
        }
    ],
    "cleanup": [
        "/include",
        "/lib/pkgconfig"
    ],
    "modules": [
        "../pipewire/pipewire-jack.json",
        "../liblo/liblo.json"
    ]
}