{
    "name": "python-dependencies",
    "buildsystem": "simple",
    "build-commands": [],
    "modules": [
        {
            "name": "python3-PyOpenGL",
            "buildsystem": "simple",
            "build-commands": [
                "pip3 install --exists-action=i --no-index --find-links=\"file://${PWD}\" --prefix=${FLATPAK_DEST} \"PyOpenGL\" --no-build-isolation"
            ],
            "sources": [
                {
                    "type": "file",
                    "url": "https://files.pythonhosted.org/packages/b8/73/31c8177f3d236e9a5424f7267659c70ccea604dab0585bfcd55828397746/PyOpenGL-3.1.5.tar.gz",
                    "sha256": "4107ba0d0390da5766a08c242cf0cf3404c377ed293c5f6d701e457c57ba3424"
                }
            ]
        },
        {
            "name": "python3-PyYAML",
            "buildsystem": "simple",
            "build-commands": [
                "pip3 install --exists-action=i --no-index --find-links=\"file://${PWD}\" --prefix=${FLATPAK_DEST} \"PyYAML\" --no-build-isolation"
            ],
            "sources": [
                {
                    "type": "file",
                    "url": "https://files.pythonhosted.org/packages/a0/a4/d63f2d7597e1a4b55aa3b4d6c5b029991d3b824b5bd331af8d4ab1ed687d/PyYAML-5.4.1.tar.gz",
                    "sha256": "607774cbba28732bfa802b54baa7484215f530991055bb562efbed5b2f20a45e"
                }
            ]
        },
        {
            "name": "python3-numpy",
            "buildsystem": "simple",
            "build-commands": [
                "pip3 install --exists-action=i --no-index --find-links=\"file://${PWD}\" --prefix=${FLATPAK_DEST} \"numpy\" --no-build-isolation"
            ],
            "sources": [
                {
                    "type": "file",
                    "url": "https://files.pythonhosted.org/packages/82/a8/1e0f86ae3f13f7ce260e9f782764c16559917f24382c74edfb52149897de/numpy-1.20.2.zip",
                    "sha256": "878922bf5ad7550aa044aa9301d417e2d3ae50f0f577de92051d739ac6096cee"
                }
            ]
        }
    ]
}